nipraxis/__init__.py
nipraxis/_fetcher.py
nipraxis/registry.yaml
nipraxis/rotations.py
nipraxis/stimuli.py
nipraxis/tests/__init__.py
nipraxis/tests/test_local_cache.py
nipraxis/tests/test_rotations.py
nipraxis/tests/test_stimuli.py
nipraxis-0.4.1.dist-info/LICENSE
nipraxis-0.4.1.dist-info/WHEEL
nipraxis-0.4.1.dist-info/METADATA
nipraxis-0.4.1.dist-info/RECORD
