Metadata-Version: 2.1
Name: nipraxis
Version: 0.4.1
Summary: Nipraxis utilities
Author-email: The Nipraxis team <matthew.brett@gmail.com>
Classifier: License :: OSI Approved :: BSD License
Classifier: Programming Language :: Python :: 3
Requires-Dist: numpy
Requires-Dist: unscrewed
Requires-Dist: pytest ; extra == "test"
Project-URL: Home, https://nipraxis.org
Provides-Extra: test
